{
  "$schema": "https://developer.microsoft.com/json-schemas/core-build/serve.schema.json",
  "port": 4321,
  "https": true,
  "serveConfigurations": {
    "default": {
      "pageUrl": "https://pragdigi.sharepoint.com/sites/dev/Lists/SalesTracking/AllItems.aspx",
      "fieldCustomizers": {
        "Progress": {
          "id": "176b5714-1d35-447b-bbf5-59ad916ce66a",
          "properties": {
            "greenStatus": "85",
            "yellowStatus": "70"
          }
        }
      }
    },
    "columnVisualStatus": {
      "pageUrl": "https://contoso.sharepoint.com/sites/mySite/SitePages/myPage.aspx",
      "fieldCustomizers": {
        "InternalFieldName": {
          "id": "176b5714-1d35-447b-bbf5-59ad916ce66a",
          "properties": {
            "greenStatus": "85",
            "yellowStatus": "70"
          }
        }
      }
    }
  }
}
